pandahub/__init__.py
pandahub/api/__init__.py
pandahub/api/dependencies.py
pandahub/api/main.py
pandahub/api/settings.py
pandahub/api/internal/__init__.py
pandahub/api/internal/db.py
pandahub/api/internal/schemas.py
pandahub/api/internal/users.py
pandahub/api/routers/__init__.py
pandahub/api/routers/auth.py
pandahub/api/routers/net.py
pandahub/api/routers/projects.py
pandahub/api/routers/timeseries.py
pandahub/api/routers/users.py
pandahub/api/routers/variants.py
pandahub/lib/PandaHub.py
pandahub/lib/__init__.py
pandahub/lib/database_toolbox.py
pandahub/lib/datatypes.py
pandahub/lib/mongo_client.py
pandahub/lib/mongodb_indexes.py
pandahub/lib/settings.py
pandahub/lib/timeseries/__init__.py
pandahub/lib/timeseries/output_writer_mongodb.py
pandahub/lib/timeseries/data_sources/__init__.py
pandahub/lib/timeseries/data_sources/mongo_data.py
pandahub-0.5.12.dist-info/METADATA
pandahub-0.5.12.dist-info/WHEEL
pandahub-0.5.12.dist-info/licenses/LICENSE
pandahub-0.5.12.dist-info/RECORD
