Metadata-Version: 2.4
Name: pandahub
Version: 0.5.12
Summary: Data hub for pandapower and pandapipes networks based on MongoDB
Project-URL: Homepage, https://github.com/e2nIEE/pandahub
Project-URL: Documentation, https://pandapipes.readthedocs.io
Project-URL: Source, https://github.com/e2nIEE/pandahub
Project-URL: Repository, https://github.com/e2nIEE/pandahub.git
Project-URL: Issues, https://github.com/e2nIEE/pandahub/issues
Project-URL: Download, https://pypi.org/project/pandahub/#files
Project-URL: Changelog, https://github.com/e2nIEE/pandahub/blob/develop/CHANGELOG.md
Author-email: Jan Ulffers <jan.ulffers@iee.fraunhofer.de>, Leon Thurner <leon.thurner@retoflow.de>, Jannis Kupka <jannis.kupka@retoflow.de>, Mike Vogt <mike.vogt@iee.fraunhofer.de>, Joschka Thurner <joschka.thurner@retoflow.de>, Alexander Scheidler <alexander.scheidler@iee.fraunhofer.de>
License: Copyright (c) 2022 by University of Kassel, Fraunhofer Institute for Energy Economics
License-File: LICENSE
Keywords: analysis,automation,energy,engineering,grid,network,optimization,simulation
Classifier: Development Status :: 5 - Production/Stable
Classifier: Environment :: Console
Classifier: Intended Audience :: Developers
Classifier: Intended Audience :: Education
Classifier: Intended Audience :: Science/Research
Classifier: License :: OSI Approved :: BSD License
Classifier: Natural Language :: English
Classifier: Operating System :: OS Independent
Classifier: Programming Language :: Python
Classifier: Programming Language :: Python :: 3
Classifier: Programming Language :: Python :: 3.9
Classifier: Programming Language :: Python :: 3.10
Classifier: Programming Language :: Python :: 3.11
Classifier: Programming Language :: Python :: 3.12
Requires-Python: >=3.9
Requires-Dist: blosc
Requires-Dist: pandapipes>=0.7.0
Requires-Dist: pandapower>=3.0
Requires-Dist: pydantic
Requires-Dist: pydantic-settings
Requires-Dist: pymongo>=4.9
Requires-Dist: pymongoarrow
Provides-Extra: rest-api
Requires-Dist: fastapi-users[beanie]>=12.0; extra == 'rest-api'
Requires-Dist: fastapi[standard-no-fastapi-cloud-cli]>=0.104.0; extra == 'rest-api'
Provides-Extra: test
Requires-Dist: line-profiler; extra == 'test'
Requires-Dist: pytest; extra == 'test'
Requires-Dist: pytest-xdist; extra == 'test'
Requires-Dist: simbench; extra == 'test'
